easy_di/__init__.py
easy_di/di_storage.py
easy_di/exceptions.py
easy_di/injection.py
easy_di/loaders_patching.py
easy_di/main.py
easy_di/resource_locator.py
easy_dependency_injection-0.2.0.dist-info/LICENSE
easy_dependency_injection-0.2.0.dist-info/METADATA
easy_dependency_injection-0.2.0.dist-info/WHEEL
easy_dependency_injection-0.2.0.dist-info/top_level.txt
easy_dependency_injection-0.2.0.dist-info/RECORD
