Metadata-Version: 2.1
Name: easy-dependency-injection
Version: 0.2.0
Summary: Easy to use Dependency Injection Library
Author-email: Iacopo Papalini <iacopo@domotz.com>
License: MIT
Project-URL: homepage, https://github.com/domotz/easy-di
Project-URL: repository, https://github.com/domotz/easy-di
Keywords: dependency-injection,inversion-of-control,di
Classifier: License :: OSI Approved :: MIT License
Classifier: Programming Language :: Python
Classifier: Programming Language :: Python :: 3
Requires-Python: >=3.8
License-File: LICENSE
Provides-Extra: dev
Requires-Dist: bandit ; extra == 'dev'
Requires-Dist: black ; extra == 'dev'
Requires-Dist: bumpver ; extra == 'dev'
Requires-Dist: isort ; extra == 'dev'
Requires-Dist: pytest ; extra == 'dev'
